{"generated_at":"2026-05-04T14:57:36Z","data_hash":"4da1e9b5f2c59bd9","output_format":"json","version":"v0.16.0","id":"hp-s00","title":"Phase 5: Plan quality tracker (intent / architecture / workflow / implementation / testing / risk / bead-readiness)","score":0.18834207922380522,"reasons":["🔓 Unblocks 2 item(s): hp-rsly, hp-x3z","✅ Currently unclaimed - available for work","🚨 High priority (P1) - prioritize this work"],"unblocks":2,"claim_command":"br update hp-s00 --status=in_progress","show_command":"br show hp-s00"}
